octodns_yandex/__init__.py
octodns_yandex/auth.py
octodns_yandex/exception.py
octodns_yandex/exceptions.py
octodns_yandex/mappings.py
octodns_yandex/record.py
octodns_yandex/version.py
octodns_yandex/yandex360_provider.py
octodns_yandex/yandexcloud_cdn_source.py
octodns_yandex/yandexcloud_cm_source.py
octodns_yandex/yandexcloud_provider.py
tests/__init__.py
tests/grpc_server_mock.py
tests/test_auth.py
tests/test_provider_octodns_yandex360.py
tests/test_provider_octodns_yandexcloud.py
tests/test_source_octodns_yandexcloud_cdn.py
tests/test_source_octodns_yandexcloud_cm.py
tests/utils.py
tests/fixtures/__init__.py
tests/fixtures/cdn_resources.py
tests/fixtures/certificates.py
tests/fixtures/dns_zones.py
tests/fixtures/dns_zones_idna.py
tests/fixtures/record_sets.py
tests/fixtures/record_sets_idna.py
tests/fixtures/ya360.py
octodns_yandex-0.0.3.dist-info/LICENSE
octodns_yandex-0.0.3.dist-info/METADATA
octodns_yandex-0.0.3.dist-info/WHEEL
octodns_yandex-0.0.3.dist-info/top_level.txt
octodns_yandex-0.0.3.dist-info/RECORD
