Metadata-Version: 2.1
Name: octodns-yandex
Version: 0.0.3
Summary: [![PyPI Version][pypi-image]][pypi-url]
Home-page: https://github.com/90victor09/octodns-yandex
Author: Victor Scherbackov
Author-email: victor@90victor09.ru
License: MIT
Requires-Python: >=3.8
License-File: LICENSE
Requires-Dist: octodns >=1.0.0
Requires-Dist: protobuf <5.0.0.dev0
Requires-Dist: yandexcloud >=0.270.0
Requires-Dist: requests >=2.27.0
Provides-Extra: dev
Requires-Dist: pytest ; extra == 'dev'
Requires-Dist: pytest-cov ; extra == 'dev'
Requires-Dist: pytest-network ; extra == 'dev'
Requires-Dist: black <24.0.0,>=23.1.0 ; extra == 'dev'
Requires-Dist: build >=0.7.0 ; extra == 'dev'
Requires-Dist: isort >=5.11.5 ; extra == 'dev'
Requires-Dist: pyflakes >=2.2.0 ; extra == 'dev'
Requires-Dist: readme-renderer[md] >=26.0 ; extra == 'dev'
Requires-Dist: twine >=3.4.2 ; extra == 'dev'
Provides-Extra: test
Requires-Dist: pytest ; extra == 'test'
Requires-Dist: pytest-cov ; extra == 'test'
Requires-Dist: pytest-network ; extra == 'test'
